FcBypass/__init__.py
FcBypass/bypass.py
fcbypass-1.0.6.dist-info/LICENSE
fcbypass-1.0.6.dist-info/METADATA
fcbypass-1.0.6.dist-info/WHEEL
fcbypass-1.0.6.dist-info/top_level.txt
fcbypass-1.0.6.dist-info/RECORD
