Metadata-Version: 2.1
Name: fcbypass
Version: 1.0.6
Summary: A package to get Solved Funcaptcha tokens for Roblox.
Home-page: https://github.com/Vertable/fcbypass
Author: Vertable
Author-email: author@example.com
Project-URL: Bug Tracker, https://github.com/Vertable/fcbypass/issues
Classifier: Programming Language :: Python :: 3
Classifier: License :: OSI Approved :: MIT License
Classifier: Operating System :: OS Independent
Requires-Python: >=3.6
License-File: LICENSE
